overpython/__init__.py
overpython/overpython.py
overpython-1.1.1.dist-info/LICENSE
overpython-1.1.1.dist-info/METADATA
overpython-1.1.1.dist-info/WHEEL
overpython-1.1.1.dist-info/top_level.txt
overpython-1.1.1.dist-info/RECORD
