Metadata-Version: 2.1
Name: overpython
Version: 1.1.1
Summary: A pointless package designed to overcomplicate Python
Home-page: https://github.com/host12prog/overpython/
Author: supernova
Author-email: tomfleetwitter@gmail.com
License: UNKNOWN
Platform: UNKNOWN
Classifier: Programming Language :: Python :: 3
Classifier: License :: OSI Approved :: MIT License
Classifier: Operating System :: OS Independent
Requires-Python: >=3.6
